main.py
IlubluAlexandraShahova_task_4-1.0.0.dist-info/METADATA
IlubluAlexandraShahova_task_4-1.0.0.dist-info/WHEEL
IlubluAlexandraShahova_task_4-1.0.0.dist-info/top_level.txt
IlubluAlexandraShahova_task_4-1.0.0.dist-info/RECORD
