Metadata-Version: 2.1
Name: IlubluAlexandraShahova_task_4
Version: 1.0.0
Summary: IlubluAlexandraShahova_task_4
Author-email: Gleb <glebnikolenko9@gmail.com>
Requires-Python: >=3.6
